ql-2.4.6.dist-info/METADATA
ql-2.4.6.dist-info/WHEEL
ql-2.4.6.dist-info/entry_points.txt
ql-2.4.6.dist-info/licenses/LICENSE
quill/__init__.py
quill/__share__.py
quill/cyl.ini
quill/fold/README.md
quill/fold/__init__.py
quill/fold/auditing.py
quill/fold/cli.py
quill/fold/cut/__init__.py
quill/fold/cut/audit_checking.py
quill/fold/cut/contexts/__init__.py
quill/fold/cut/contexts/article.py
quill/fold/cut/contexts/base.py
quill/fold/cut/contexts/helpers.py
quill/fold/cut/contexts/index.py
quill/fold/cut/contexts/md.py
quill/fold/cut/contexts/models.py
quill/fold/cut/ctx.py
quill/fold/cut/ctx_building.py
quill/fold/cut/datetime_util.py
quill/fold/cut/interface.py
quill/fold/cut/main.py
quill/fold/cut/name_config.py
quill/fold/cut/pymd_engine.py
quill/fold/cut/rules.py
quill/fold/cut/templater.py
quill/fold/distrib_setup.py
quill/fold/git.py
quill/fold/man.py
quill/fold/ns_util.py
quill/fold/site_yaml.py
quill/fold/subdomain.py
quill/fold/wire/__init__.py
quill/fold/wire/emitters.ini
quill/fold/wire/emitters.py
quill/fold/wire/html_elem_util.py
quill/fold/wire/html_index_util.py
quill/fold/wire/html_page_util.py
quill/fold/wire/html_util.py
quill/fold/wire/main.py
quill/fold/wire/sinks.py
quill/fold/wire/transforms.py
quill/fold/yaml_util.py
quill/manifest/README.md
quill/manifest/__init__.py
quill/manifest/man.py
quill/manifest/namings.py
quill/manifest/parsing.py
quill/scan/README.md
quill/scan/__init__.py
quill/scan/address/__init__.py
quill/scan/address/paths.py
quill/scan/address/routing.py
quill/scan/io.py
quill/scan/lever/__init__.py
quill/scan/lever/blockelems.py
quill/scan/lever/docelems.py
quill/scan/lever/elems.py
quill/scan/lever/git.py
quill/scan/lever/lists.py
quill/scan/lever/mmd.py
quill/scan/lever/parser.py
quill/scan/lever/structure.py
quill/scan/lever/tokens.py
quill/spin.ini
ql-2.4.6.dist-info/RECORD
