Metadata-Version: 2.1
Name: ql
Version: 2.4.6
Summary: spin.systems generator and driver
Keywords: website,staticjinja
Author-Email: Louis Maddox <louismmx@gmail.com>
License: MIT
Classifier: Development Status :: 6 - Mature
Classifier: License :: OSI Approved :: MIT License
Classifier: Operating System :: OS Independent
Classifier: Intended Audience :: Developers
Classifier: Natural Language :: English
Classifier: Topic :: Internet :: WWW/HTTP :: Site Management
Classifier: Programming Language :: Python
Classifier: Programming Language :: Python :: 3.10
Classifier: Programming Language :: Python :: 3.11
Classifier: Programming Language :: Python :: 3.12
Project-URL: Homepage, https://github.com/spin-systems/quill
Project-URL: Repository, https://github.com/spin-systems/quill.git
Requires-Python: <3.13,>=3.10
Requires-Dist: defopt
Requires-Dist: pandas
Requires-Dist: parse
Requires-Dist: pyyaml
Requires-Dist: gitpython
Requires-Dist: bs4
Requires-Dist: html5lib
Requires-Dist: aenum
Requires-Dist: staticjinja
Requires-Dist: markdown
Requires-Dist: pygments
Requires-Dist: python-frontmatter
Requires-Dist: dateparser
Requires-Dist: markdown-katex>=202112.1034
Requires-Dist: pathlib2
Requires-Dist: pydantic>=2.5.2
Requires-Dist: ocxsect>=0.1.5
